urllib3-stubs/METADATA.toml
urllib3-stubs/__init__.pyi
urllib3-stubs/_collections.pyi
urllib3-stubs/connection.pyi
urllib3-stubs/connectionpool.pyi
urllib3-stubs/exceptions.pyi
urllib3-stubs/fields.pyi
urllib3-stubs/filepost.pyi
urllib3-stubs/poolmanager.pyi
urllib3-stubs/request.pyi
urllib3-stubs/response.pyi
urllib3-stubs/contrib/__init__.pyi
urllib3-stubs/contrib/socks.pyi
urllib3-stubs/packages/__init__.pyi
urllib3-stubs/packages/ssl_match_hostname/__init__.pyi
urllib3-stubs/packages/ssl_match_hostname/_implementation.pyi
urllib3-stubs/util/__init__.pyi
urllib3-stubs/util/connection.pyi
urllib3-stubs/util/queue.pyi
urllib3-stubs/util/request.pyi
urllib3-stubs/util/response.pyi
urllib3-stubs/util/retry.pyi
urllib3-stubs/util/ssl_.pyi
urllib3-stubs/util/timeout.pyi
urllib3-stubs/util/url.pyi
types_urllib3-1.26.25.9.dist-info/METADATA
types_urllib3-1.26.25.9.dist-info/WHEEL
types_urllib3-1.26.25.9.dist-info/top_level.txt
types_urllib3-1.26.25.9.dist-info/RECORD
